cicd/__init__.py
cicd/__main__.py
cicd/cicd.py
cicd/config.ini
cicd/utils/__init__.py
cicd/utils/config.py
cicd/utils/decorators.py
cicd/utils/dwhrepo.py
cicd/utils/log.py
cicd/utils/model.py
cicd/utils/release.py
cicd/utils/snowflake.py
cicd/utils/sql.py
cicd/utils/utils.py
snowflake_cicd-0.1.3.dist-info/LICENSE.txt
snowflake_cicd-0.1.3.dist-info/METADATA
snowflake_cicd-0.1.3.dist-info/WHEEL
snowflake_cicd-0.1.3.dist-info/entry_points.txt
snowflake_cicd-0.1.3.dist-info/top_level.txt
snowflake_cicd-0.1.3.dist-info/RECORD
