Metadata-Version: 2.1
Name: snowflake-cicd
Version: 0.1.3
Summary: Snowflake CI/CD utility
Home-page: https://github.com/szn/snowflake-cicd
Author: Szymon Nieradka
License: MIT
Download-URL: https://github.com/szn/snowflake-cicd/archive/refs/tags/v0.1.3.tar.gz
Keywords: snowflake,cicd
Platform: UNKNOWN
Classifier: Programming Language :: Python :: 3
Classifier: Programming Language :: Python :: 3.7
Classifier: Programming Language :: Python :: 3.8
Classifier: Programming Language :: Python :: 3.9
Classifier: Development Status :: 3 - Alpha
Classifier: License :: OSI Approved :: MIT License
Classifier: Intended Audience :: Developers
Classifier: Topic :: Software Development :: Build Tools
License-File: LICENSE.txt
Requires-Dist: GitPython
Requires-Dist: snowflake-connector-python
Requires-Dist: coloredlogs
Requires-Dist: sqlparse
Requires-Dist: termcolor
Requires-Dist: importlib ; python_version == "3.7"
